{"stats":{"minecraft:used":{"ironchest:wood_to_iron_chest_upgrade":1,"minecraft:carved_pumpkin":5,"minecraft:ladder":8,"create:cut_limestone_slab":1,"minecraft:chest":2,"minecraft:shield":6,"minecraft:iron_sword":36,"minecraft:cooked_salmon":2,"minecraft:rotten_flesh":2,"minecraft:torch":27,"minecraft:carrot":36,"born_in_chaos_v1:corpse_maggot":2,"minecraft:iron_block":21,"minecraft:iron_axe":149,"minecraft:bow":80,"minecraft:dark_oak_boat":1,"minecraft:sweet_berries":74,"minecraft:cooked_cod":1,"ironchest:gold_chest":1,"minecraft:potato":8,"minecraft:powder_snow_bucket":2,"minecraft:pumpkin":4,"minecraft:wheat_seeds":24,"minecraft:water_bucket":30,"minecraft:cookie":32,"minecraft:crafting_table":2,"minecraft:white_bed":1,"minecraft:shears":10,"relics:horse_flute":8,"minecraft:bread":21,"minecraft:iron_pickaxe":186,"ironchest:iron_to_gold_chest_upgrade":1,"minecraft:polished_andesite_slab":1,"minecraft:cobblestone":16,"minecraft:bucket":34,"alexsmobs:animal_dictionary":8},"minecraft:picked_up":{"pointblank:ammo50bmg":2,"sophisticatedbackpacks:gold_backpack":1,"luminousworld:groundpebbles_1":5,"minecraft:crafting_table":1,"minecraft:wheat":27,"minecraft:ladder":4,"minecraft:chicken":1,"minecraft:brown_mushroom":9,"minecraft:gold_block":4,"crittersandcompanions:grappling_hook":3,"minecraft:string":16,"minecraft:iron_axe":1,"legendary_monsters:ancient_spike":3,"minecraft:cooked_salmon":2,"create:cut_limestone_slab":1,"regions_unexplored:pine_log":11,"furniture:trash_bag":3,"minecraft:spruce_planks":7,"legendary_monsters:ancient_dripstone_block":6,"crittersandcompanions:koi_fish":1,"minecraft:iron_nugget":4,"minecraft:chest":1,"pointblank:gunmetal_ingot":64,"minecraft:stick":6,"regions_unexplored:silver_birch_leaf_pile":14,"minecraft:copper_ingot":26,"minecraft:torch":1,"pointblank:gunmetal_nugget":74,"ironchest:gold_chest":1,"minecraft:carrot":36,"legendary_monsters:ancient_dripstone_bricks":5,"minecraft:dark_oak_planks":3,"pointblank:aug":3,"minecraft:arrow":14,"minecraft:rotten_flesh":38,"minecraft:cooked_cod":1,"minecraft:beetroot_seeds":33,"minecraft:pumpkin_pie":12,"relics:horse_flute":1,"minecraft:carved_pumpkin":9,"minecraft:iron_block":27,"minecraft:gold_ingot":36,"croptopia:pecan":4,"minecraft:cobblestone":138,"born_in_chaos_v1:corpse_maggot":2,"relics:roller_skates":1,"pointblank:guninternals":52,"pointblank:jatimatic_skin_artisanal":1,"minecraft:dark_oak_boat":2,"minecraft:potato":52,"regions_unexplored:salmon_poppy_bush":2,"minecraft:dirt":9,"minecraft:paper":2,"minecraft:bone":16,"minecraft:kelp":76,"minecraft:bow":5,"minecraft:wheat_seeds":117,"minecraft:iron_ingot":175,"minecraft:cobweb":1,"pointblank:spr2":1,"minecraft:polished_andesite_slab":1,"grimoireofgaia:zombie_staff":1,"pointblank:cp2077_rostovic_kolac_mike":1,"pointblank:ammo556":168,"minecraft:pumpkin":4,"minecraft:sweet_berries":63,"legendary_monsters:ancient_dripstone_brick_stairs":1,"minecraft:dark_oak_log":8,"minecraft:spider_eye":2,"immersive_melodies:piano":1,"minecraft:pumpkin_seeds":32,"legendary_monsters:ancient_dripstone_tile_slab":2,"minecraft:diamond":2,"regions_unexplored:silver_birch_log":23,"goety:spider_egg":2,"minecraft:bread":18,"minecraft:coal":69},"minecraft:crafted":{"minecraft:dark_oak_boat":2,"minecraft:ladder":6,"minecraft:chest":1,"minecraft:dark_oak_planks":20,"ironchest:wood_to_iron_chest_upgrade":1,"minecraft:crafting_table":1,"minecraft:bucket":2,"ironchest:iron_to_gold_chest_upgrade":1,"minecraft:stick":4,"minecraft:iron_block":5,"minecraft:torch":88,"minecraft:shears":2},"minecraft:killed":{"undead_revamp2:thehunter":1,"minecraft:spider":6,"born_in_chaos_v1:maggot":2,"minecraft:skeleton":5,"luminousworld:dark_oak_skeleton":1,"minecraft:chicken":1,"enemyexpansion:goblin":2,"born_in_chaos_v1:glutton_fish":2,"minecraft:iron_golem":1,"born_in_chaos_v1:decrepit_skeleton":1,"born_in_chaos_v1:decaying_zombie":1,"minecraft:zombie":2,"legendary_monsters:spiky_bug":7,"grimoireofgaia:deathword":1,"born_in_chaos_v1:corpse_fly":4,"enemyexpansion:botfly":1},"minecraft:mined":{"minecraft:dark_oak_planks":3,"minecraft:spruce_planks":7,"minecraft:dark_oak_log":5,"minecraft:carved_pumpkin":11,"minecraft:ladder":3,"minecraft:stone_brick_wall":3,"minecraft:brown_mushroom_block":4,"minecraft:kelp":2,"luminousworld:groundpebbles_3":1,"legendary_monsters:ancient_dripstone_tiles":1,"legendary_monsters:ancient_dripstone_tile_slab":2,"minecraft:carrots":12,"ironchest:gold_chest":1,"minecraft:pumpkin":4,"regions_unexplored:frozen_grass":1,"regions_unexplored:pine_leaves":8,"minecraft:potatoes":16,"regions_unexplored:maple_leaf_pile":3,"regions_unexplored:medium_grass":1,"regions_unexplored:orange_maple_leaf_pile":1,"minecraft:stone":69,"minecraft:iron_block":1,"legendary_monsters:ancient_dripstone_brick_stairs":1,"minecraft:kelp_plant":5,"regions_unexplored:silver_birch_leaf_pile":8,"legendary_monsters:ancient_dripstone_block":6,"minecraft:powder_snow":2,"minecraft:crafting_table":1,"regions_unexplored:salmon_poppy_bush":1,"minecraft:chest":1,"minecraft:cobblestone":7,"regions_unexplored:pine_log":11,"minecraft:sea_pickle":1,"minecraft:wheat":54,"minecraft:sweet_berry_bush":20,"regions_unexplored:red_maple_leaf_pile":1,"minecraft:grass":6,"minecraft:coal_ore":69,"minecraft:beetroots":4,"regions_unexplored:silver_birch_log":23,"minecraft:dirt":9,"minecraft:cobweb":6,"minecraft:oak_leaves":1,"legendary_monsters:ancient_dripstone_bricks":5},"minecraft:broken":{"minecraft:iron_helmet":1},"minecraft:dropped":{"minecraft:iron_ingot":6,"minecraft:bread":1,"minecraft:brown_mushroom":6,"minecraft:wheat_seeds":52,"pointblank:gunmetal_ingot":38,"minecraft:cobblestone":25,"pointblank:jatimatic_skin_artisanal":1,"relics:horse_flute":1,"pointblank:aug":3,"minecraft:stick":7,"relics:roller_skates":1,"regions_unexplored:salmon_poppy_bush":2,"pointblank:guninternals":43,"regions_unexplored:silver_birch_leaf_pile":14,"minecraft:paper":2,"minecraft:string":3,"minecraft:dark_oak_boat":1,"minecraft:bone":2,"furniture:trash_bag":1,"minecraft:kelp":57,"minecraft:sweet_berries":14,"minecraft:iron_nugget":3,"minecraft:rotten_flesh":15,"minecraft:carrot":24,"minecraft:pumpkin_seeds":16,"pointblank:gunmetal_nugget":4,"minecraft:potato":62,"crittersandcompanions:koi_fish":2,"luminousworld:groundpebbles_1":4,"minecraft:beetroot_seeds":33,"pointblank:spr2":1,"pointblank:cp2077_rostovic_kolac_mike":1,"minecraft:bow":3,"crittersandcompanions:grappling_hook":2},"minecraft:killed_by":{"minecraft:player":1,"born_in_chaos_v1:nightmare_stalker":1,"grimoireofgaia:minotaurus":1,"minecraft:zombie":1},"minecraft:custom":{"minecraft:interact_with_anvil":1,"minecraft:mob_kills":40,"minecraft:animals_bred":5,"minecraft:interact_with_crafting_table":25,"minecraft:open_barrel":2,"minecraft:interact_with_campfire":3,"minecraft:damage_dealt_resisted":127,"minecraft:leave_game":7,"minecraft:time_since_death":16944,"minecraft:climb_one_cm":8303,"minecraft:sprint_one_cm":822670,"minecraft:walk_one_cm":2132250,"minecraft:damage_blocked_by_shield":30,"minecraft:drop":89,"minecraft:talked_to_villager":1,"minecraft:play_time":327195,"minecraft:deaths":7,"minecraft:sneak_time":13273,"minecraft:walk_under_water_one_cm":42598,"minecraft:jump":1352,"minecraft:walk_on_water_one_cm":52222,"minecraft:total_world_time":327195,"minecraft:interact_with_furnace":3,"spartanshields:shield_bash_hits":2,"minecraft:sleep_in_bed":3,"minecraft:time_since_rest":10078,"minecraft:waystone_activated":1,"minecraft:damage_taken":9162,"minecraft:damage_dealt":927,"minecraft:swim_one_cm":267137,"minecraft:fly_one_cm":261801,"minecraft:open_chest":35,"minecraft:crouch_one_cm":72816,"minecraft:fall_one_cm":54948}},"DataVersion":3465}