{"stats":{"minecraft:custom":{"minecraft:jump":81,"minecraft:time_since_rest":6207,"minecraft:damage_dealt":6,"minecraft:sprint_one_cm":14629,"minecraft:deaths":7,"minecraft:damage_taken":7000,"minecraft:play_time":12819,"minecraft:walk_on_water_one_cm":25631,"minecraft:time_since_death":7888,"minecraft:walk_one_cm":15556,"minecraft:sleep_in_bed":1,"minecraft:total_world_time":12819,"minecraft:walk_under_water_one_cm":23598,"minecraft:swim_one_cm":7085,"minecraft:fall_one_cm":267,"minecraft:fly_one_cm":16586},"minecraft:killed_by":{"born_in_chaos_v1:corpse_fish":1,"grimoireofgaia:cecaelia":6},"minecraft:mined":{"minecraft:kelp_plant":2}},"DataVersion":3465}